aecg/__init__.py
aecg/maps.py
aecg/models.py
aecg/parser.py
aecg/plotter.py
aecg/utils.py
aecg-0.1.2.dist-info/METADATA
aecg-0.1.2.dist-info/WHEEL
aecg-0.1.2.dist-info/top_level.txt
aecg-0.1.2.dist-info/RECORD
