Metadata-Version: 2.4
Name: aecg
Version: 0.1.2
Summary: Python parser and viewer for Annotated ECG HL7 files
Author-email: Ghiles Meddour <ghiles.meddour.b@gmail.com>
Project-URL: Repository, https://github.com/ghilesmeddour/aecg
Project-URL: Documentation, https://github.com/ghilesmeddour/aecg
Project-URL: Changelog, https://github.com/ghilesmeddour/aecg/blob/main/CHANGELOG.md
Project-URL: Releases, https://github.com/ghilesmeddour/aecg/releases
Requires-Python: >=3.12
Requires-Dist: lxml>=5.3.0
Requires-Dist: pandas>=2.2.3
Requires-Dist: plotly>=5.24.1
Requires-Dist: pydantic-xml<2.18.0,>=2.13.1
Requires-Dist: pydantic>=2.9.2
Requires-Dist: python-benedict[xml]>=0.34.0
Provides-Extra: dev
Requires-Dist: coverage>=7.8.0; extra == "dev"
Requires-Dist: devtools>=0.12.2; extra == "dev"
Requires-Dist: pytest>=8.3.3; extra == "dev"
Requires-Dist: ruff>=0.6.9; extra == "dev"
